felt_python/__init__.py
felt_python/api.py
felt_python/comments.py
felt_python/elements.py
felt_python/exceptions.py
felt_python/layer_groups.py
felt_python/layers.py
felt_python/library.py
felt_python/maps.py
felt_python/projects.py
felt_python/sources.py
felt_python/user.py
felt_python/util.py
felt_python-0.1.3.dist-info/METADATA
felt_python-0.1.3.dist-info/WHEEL
felt_python-0.1.3.dist-info/licenses/LICENSE
felt_python-0.1.3.dist-info/RECORD
