Metadata-Version: 2.4
Name: felt-python
Version: 0.1.3
Summary: The official Felt API client library
Project-URL: Homepage, https://github.com/felt/felt-python
Project-URL: Issues, https://github.com/felt/felt-python/issues
Project-URL: Documentation, https://developers.felt.com
Author-email: Álvaro Arredondo <alvaro@felt.com>, Vince Foley <vince@felt.com>, Chris Loer <chris@felt.com>
License-File: LICENSE
Classifier: License :: OSI Approved :: MIT License
Classifier: Operating System :: OS Independent
Classifier: Programming Language :: Python :: 3
Requires-Python: >=3.6
